Metadata-Version: 2.1
Name: webshoter
Version: 1.0.4
Summary: A python tool to take screenshots for urls
Home-page: https://github.com/americo/webshoter
Download-URL: https://github.com/americo/webshoter/archive/v1.0.4.zip
Author: americo
License: MIT License
Keywords: screenshot,web,recon
Classifier: Topic :: Security
Classifier: Operating System :: OS Independent
Classifier: License :: OSI Approved :: MIT License
Classifier: Programming Language :: Python :: 3
License-File: LICENSE
